README.md
setup.py
bth5/__init__.py
bth5/dataset.py
bth5.egg-info/PKG-INFO
bth5.egg-info/SOURCES.txt
bth5.egg-info/dependency_links.txt
bth5.egg-info/requires.txt
bth5.egg-info/top_level.txt
bth5.egg-info/zip-safe