Metadata-Version: 2.1
Name: bth5
Version: 0.0.1
Summary: Bitemporal HDF5
Home-page: https://github.com/quansight/bitemporal-h5
Author: Anthony Scopatz
Author-email: scopatz@gmail.com
Maintainer: Quansight
License: BSD-3-Clause
Platform: Cross Platform
Classifier: Programming Language :: Python :: 3
Provides-Extra: tests
